jeff_api_common/__init__.py
jeff_api_common/api/__init__.py
jeff_api_common/api/server.py
jeff_api_common/auth/__init__.py
jeff_api_common/auth/auth.py
jeff_api_common/client/__init__.py
jeff_api_common/common/__init__.py
jeff_api_common/foo/__init__.py
jeff_api_common-0.1.5.dist-info/METADATA
jeff_api_common-0.1.5.dist-info/WHEEL
jeff_api_common-0.1.5.dist-info/RECORD
